elasticmetrics/__init__.py
elasticmetrics/collectors.py
elasticmetrics/exceptions.py
elasticmetrics/formatters.py
elasticmetrics/http.py
elasticmetrics/metrics.py
elasticmetrics/tool.py
elasticmetrics/pystdlib/__init__.py
elasticmetrics/pystdlib/urllib_request.py
elasticmetrics-0.1.1.dist-info/LICENSE
elasticmetrics-0.1.1.dist-info/METADATA
elasticmetrics-0.1.1.dist-info/WHEEL
elasticmetrics-0.1.1.dist-info/top_level.txt
elasticmetrics-0.1.1.dist-info/zip-safe
elasticmetrics-0.1.1.dist-info/RECORD
